torch_tomogram/__init__.py
torch_tomogram/py.typed
torch_tomogram/tomogram.py
torch_tomogram-0.0.1.dist-info/METADATA
torch_tomogram-0.0.1.dist-info/WHEEL
torch_tomogram-0.0.1.dist-info/licenses/LICENSE
torch_tomogram-0.0.1.dist-info/RECORD
